ipinfooo/README.md
ipinfooo/__init__.py
ipinfooo/requirements.txt
ipinfooo/thirdparty.json
ipinfooo-0.10.dist-info/LICENSE.rst
ipinfooo-0.10.dist-info/METADATA
ipinfooo-0.10.dist-info/WHEEL
ipinfooo-0.10.dist-info/top_level.txt
ipinfooo-0.10.dist-info/RECORD
