Metadata-Version: 2.1
Name: ipinfooo
Version: 0.10
Summary: Uses ctypes to get the IP configuration
Home-page: https://github.com/hansalemaos/ipinfooo
Author: Johannes Fischer
Author-email: aulasparticularesdealemaosp@gmail.com
License: MPL
Keywords: ctypes,ip,configuration
Classifier: Development Status :: 4 - Beta
Classifier: Programming Language :: Python :: 3 :: Only
Classifier: Programming Language :: Python :: 3.10
Classifier: Topic :: Software Development :: Libraries :: Python Modules
Classifier: Topic :: Utilities
License-File: LICENSE.rst
Requires-Dist: six
